llamacloud/__init__.py
llamacloud/llamacloud.py
llamacloud_python-0.1.1.dist-info/METADATA
llamacloud_python-0.1.1.dist-info/WHEEL
llamacloud_python-0.1.1.dist-info/licenses/LICENSE
llamacloud_python-0.1.1.dist-info/RECORD
