Metadata-Version: 2.4
Name: llamacloud-python
Version: 0.1.1
Summary: Python client for LlamaCloud AI APIs
Project-URL: Homepage, https://github.com/brilliantai/llamacloud
Project-URL: Bug Tracker, https://github.com/brilliantai/llamacloud/issues
Author: Jennifer Umoke
License-File: LICENSE
Classifier: License :: OSI Approved :: MIT License
Classifier: Operating System :: OS Independent
Classifier: Programming Language :: Python :: 3
Classifier: Programming Language :: Python :: 3.8
Classifier: Programming Language :: Python :: 3.9
Classifier: Programming Language :: Python :: 3.10
Classifier: Programming Language :: Python :: 3.11
Requires-Python: >=3.8
Requires-Dist: httpx>=0.24.0
